sas/__init__.py
sas/cosmosdb/__init__.py
sas/cosmosdb/base/__init__.py
sas/cosmosdb/base/model_base.py
sas/cosmosdb/base/repository_base.py
sas/cosmosdb/mongo/__init__.py
sas/cosmosdb/mongo/model.py
sas/cosmosdb/mongo/repository.py
sas/cosmosdb/sql/__init__.py
sas/cosmosdb/sql/model.py
sas/cosmosdb/sql/repository.py
sas_cosmosdb-0.1.4.dist-info/licenses/LICENSE
sas_cosmosdb-0.1.4.dist-info/METADATA
sas_cosmosdb-0.1.4.dist-info/WHEEL
sas_cosmosdb-0.1.4.dist-info/top_level.txt
sas_cosmosdb-0.1.4.dist-info/RECORD
