Metadata-Version: 2.4
Name: sas-cosmosdb
Version: 0.1.4
Summary: A comprehensive Python library for working with Azure Cosmos DB using both MongoDB and SQL APIs
Author-email: DB Lee <db.lee@microsoft.com>
License-Expression: MIT
Project-URL: Homepage, https://github.com/mcaps-microsoft/python_cosmosdb_helper
Project-URL: Documentation, https://github.com/mcaps-microsoft/python_cosmosdb_helper/blob/main/README.md
Project-URL: Repository, https://github.com/mcaps-microsoft/python_cosmosdb_helper
Project-URL: Issues, https://github.com/mcaps-microsoft/python_cosmosdb_helper/issues
Project-URL: Changelog, https://github.com/mcaps-microsoft/python_cosmosdb_helper/releases
Keywords: azure,cosmosdb,mongodb,sql,database,sas
Classifier: Development Status :: 4 - Beta
Classifier: Intended Audience :: Developers
Classifier: Programming Language :: Python :: 3
Classifier: Programming Language :: Python :: 3.12
Classifier: Topic :: Database
Classifier: Topic :: Software Development :: Libraries :: Python Modules
Requires-Python: >=3.12
License-File: LICENSE
Requires-Dist: aiohttp>=3.12.13
Requires-Dist: azure-appconfiguration>=1.7.1
Requires-Dist: azure-cosmos>=4.9.0
Requires-Dist: azure-identity>=1.22.0
Requires-Dist: black>=25.1.0
Requires-Dist: pydantic>=2.11.5
Requires-Dist: pydantic-settings>=2.9.1
Requires-Dist: pymongo>=4.13.2
Requires-Dist: twine>=6.0.1
Provides-Extra: dev
Requires-Dist: pytest>=8.4.0; extra == "dev"
Requires-Dist: pytest-asyncio>=1.0.0; extra == "dev"
Requires-Dist: pytest-cov>=6.2.1; extra == "dev"
Requires-Dist: black>=24.0.0; extra == "dev"
Requires-Dist: isort>=5.13.0; extra == "dev"
Requires-Dist: mypy>=1.9.0; extra == "dev"
Dynamic: license-file
